proyecto_kraken/__init__.py
proyecto_kraken/bollinger_bands.py
proyecto_kraken/kraken_client.py
proyecto_kraken/main.py
proyecto_kraken/plot_utils.py
proyecto_final_kraken-0.1.2.dist-info/METADATA
proyecto_final_kraken-0.1.2.dist-info/WHEEL
proyecto_final_kraken-0.1.2.dist-info/entry_points.txt
proyecto_final_kraken-0.1.2.dist-info/top_level.txt
proyecto_final_kraken-0.1.2.dist-info/RECORD
